{"trip":{"id":"873ca763-0473-4010-a863-0fd0bbd678af","dateUpdated":"2023-04-20T13:44:19+00:00","identifiers":{"companyId":"8a71134c-9b55-48fd-a5ee-fec5f0181192","applicationId":"75f84ece-7c8a-4b69-b5d6-307bb473c6a7","instanceId":"b7003815-6d34-4963-8731-e58f1b7a7748","userId":"610ec36b-cd57-4802-9346-f40023288f36"},"data":{"startDate":"2023-04-20T16:30:36+03:00","startDateUnixMilliseconds":1681997436000,"endDate":"2023-04-20T16:36:51+03:00","endDateUnixMilliseconds":1681997811000,"unitSystem":0,"addresses":{"start":{"full":"Chatziapostolou Nik. 34, 104 43 Athens, Greece","parts":{"countryCode":"GRC","country":"Greece","county":"Attiki","state":"Attiki","city":"Athens","district":"Athens","street":"Chatziapostolou Nik.","house":"34"}},"end":{"full":"Samou 4, 104 38 Athens, Greece","parts":{"countryCode":"GRC","country":"Greece","county":"Attiki","state":"Attiki","city":"Athens","district":"Athens","street":"Samou","house":"4"}}},"transportType":{"current":"OriginalDriver","confirmNeeded":false},"tags":[],"vehicle":null},"statistics":{"mileage":3.084291573052834,"durationMinutes":6.25,"accelerationsCount":0,"brakingsCount":1,"corneringsCount":0,"totalSpeedingMileage":0.17221011882351822,"midSpeedingMileage":0,"highSpeedingMileage":0,"phoneUsageDurationMinutes":0,"phoneUsageMileage":0,"phoneUsageWithSpeedingDurationMinutes":0,"phoneUsageWithSpeedingMileage":0,"accidentsCount":null,"dayHours":6.279366493225098,"rushHours":0,"nightHours":0,"averageSpeed":25.736611884658547,"maxSpeed":43.545166015625},"scores":{"safety":83,"acceleration":100,"braking":46,"cornering":100,"speeding":100,"phoneUsage":100,"eco":71,"ecoBrakes":0,"ecoDepreciation":25,"ecoFuel":98.81242,"ecoTyres":100},"waypoints":[{"index":0,"secSinceStart":0,"pointDateUnixMilliseconds":1681997436000,"lat":38.00146,"long":23.71113,"speed":0,"speedLimit":30,"speeding":"none","phoneUsage":false},{"index":1,"secSinceStart":3,"pointDateUnixMilliseconds":1681997439579,"lat":38.00124,"long":23.71101,"speed":0,"speedLimit":30,"speeding":"none","phoneUsage":false},{"index":2,"secSinceStart":8,"pointDateUnixMilliseconds":1681997444834,"lat":38.00091,"long":23.71084,"speed":0,"speedLimit":50,"speeding":"none","phoneUsage":false},{"index":3,"secSinceStart":10,"pointDateUnixMilliseconds":1681997446241,"lat":38.00082,"long":23.7108,"speed":0,"speedLimit":50,"speeding":"none","phoneUsage":false},{"index":4,"secSinceStart":15,"pointDateUnixMilliseconds":1681997451772,"lat":38.00047,"long":23.71063,"speed":0,"speedLimit":50,"speeding":"none","phoneUsage":false},{"index":5,"secSinceStart":20,"pointDateUnixMilliseconds":1681997456710,"lat":38.00016,"long":23.71047,"speed":0,"speedLimit":50,"speeding":"none","phoneUsage":false},{"index":6,"secSinceStart":22,"pointDateUnixMilliseconds":1681997458794,"lat":38.00003,"long":23.7104,"speed":0,"speedLimit":50,"speeding":"none","phoneUsage":false},{"index":7,"secSinceStart":24,"pointDateUnixMilliseconds":1681997460063,"lat":37.99995,"long":23.71036,"speed":0,"speedLimit":50,"speeding":"none","phoneUsage":false},{"index":8,"secSinceStart":25,"pointDateUnixMilliseconds":1681997461121,"lat":37.99988,"long":23.71034,"speed":0,"speedLimit":50,"speeding":"none","phoneUsage":false},{"index":9,"secSinceStart":26,"pointDateUnixMilliseconds":1681997462014,"lat":37.99982,"long":23.71033,"speed":0,"speedLimit":50,"speeding":"none","phoneUsage":false},{"index":10,"secSinceStart":32,"pointDateUnixMilliseconds":1681997468868,"lat":37.99968,"long":23.71089,"speed":0,"speedLimit":50,"speeding":"none","phoneUsage":false},{"index":11,"secSinceStart":48,"pointDateUnixMilliseconds":1681997484000,"lat":38.00063,"long":23.71138,"speed":0,"speedLimit":50,"speeding":"none","phoneUsage":false},{"index":12,"secSinceStart":48,"pointDateUnixMilliseconds":1681997484612,"lat":38.0007,"long":23.71142,"speed":0.7234,"speedLimit":50,"speeding":"none","phoneUsage":false},{"index":13,"secSinceStart":52,"pointDateUnixMilliseconds":1681997488484,"lat":38.00054,"long":23.71198,"speed":5.3002,"speedLimit":50,"speeding":"none","phoneUsage":false},{"index":14,"secSinceStart":54,"pointDateUnixMilliseconds":1681997490000,"lat":38.00046,"long":23.71219,"speed":7.09216,"speedLimit":50,"speeding":"none","phoneUsage":false},{"index":15,"secSinceStart":56,"pointDateUnixMilliseconds":1681997492378,"lat":38.00037,"long":23.71243,"speed":9.90301,"speedLimit":50,"speeding":"none","phoneUsage":false},{"index":16,"secSinceStart":58,"pointDateUnixMilliseconds":1681997494000,"lat":38.00032,"long":23.7126,"speed":11.82026,"speedLimit":50,"speeding":"none","phoneUsage":false},{"index":17,"secSinceStart":59,"pointDateUnixMilliseconds":1681997495000,"lat":38.00029,"long":23.71271,"speed":13.00229,"speedLimit":50,"speeding":"none","phoneUsage":false},{"index":18,"secSinceStart":60,"pointDateUnixMilliseconds":1681997496000,"lat":38.00027,"long":23.71281,"speed":14.18431,"speedLimit":50,"speeding":"none","phoneUsage":false},{"index":19,"secSinceStart":61,"pointDateUnixMilliseconds":1681997497000,"lat":38.00024,"long":23.7129,"speed":15.36634,"speedLimit":50,"speeding":"none","phoneUsage":false},{"index":20,"secSinceStart":62,"pointDateUnixMilliseconds":1681997498000,"lat":38.00021,"long":23.71301,"speed":16.54837,"speedLimit":50,"speeding":"none","phoneUsage":false},{"index":21,"secSinceStart":63,"pointDateUnixMilliseconds":1681997499000,"lat":38.00021,"long":23.71301,"speed":17.73039,"speedLimit":50,"speeding":"none","phoneUsage":false},{"index":22,"secSinceStart":64,"pointDateUnixMilliseconds":1681997500000,"lat":38.00021,"long":23.71301,"speed":18.91242,"speedLimit":50,"speeding":"none","phoneUsage":false},{"index":23,"secSinceStart":65,"pointDateUnixMilliseconds":1681997501000,"lat":38.00021,"long":23.71301,"speed":20.09444,"speedLimit":50,"speeding":"none","phoneUsage":false},{"index":24,"secSinceStart":66,"pointDateUnixMilliseconds":1681997502000,"lat":38.00026,"long":23.71304,"speed":21.27647,"speedLimit":50,"speeding":"none","phoneUsage":false},{"index":25,"secSinceStart":67,"pointDateUnixMilliseconds":1681997503000,"lat":38.00032,"long":23.71308,"speed":22.4585,"speedLimit":50,"speeding":"none","phoneUsage":false},{"index":26,"secSinceStart":68,"pointDateUnixMilliseconds":1681997504000,"lat":38.00039,"long":23.71312,"speed":23.64052,"speedLimit":50,"speeding":"none","phoneUsage":false},{"index":27,"secSinceStart":69,"pointDateUnixMilliseconds":1681997505000,"lat":38.00047,"long":23.71317,"speed":24.82255,"speedLimit":50,"speeding":"none","phoneUsage":false},{"index":28,"secSinceStart":70,"pointDateUnixMilliseconds":1681997506000,"lat":38.00055,"long":23.71322,"speed":26.00457,"speedLimit":50,"speeding":"none","phoneUsage":false},{"index":29,"secSinceStart":71,"pointDateUnixMilliseconds":1681997507000,"lat":38.00063,"long":23.71327,"speed":27.1866,"speedLimit":50,"speeding":"none","phoneUsage":false},{"index":30,"secSinceStart":72,"pointDateUnixMilliseconds":1681997508000,"lat":38.00071,"long":23.71332,"speed":27.77244,"speedLimit":50,"speeding":"none","phoneUsage":false},{"index":31,"secSinceStart":73,"pointDateUnixMilliseconds":1681997509000,"lat":38.00077,"long":23.71335,"speed":27.15317,"speedLimit":50,"speeding":"none","phoneUsage":false},{"index":32,"secSinceStart":74,"pointDateUnixMilliseconds":1681997510000,"lat":38.00081,"long":23.71338,"speed":26.4362,"speedLimit":50,"speeding":"none","phoneUsage":false},{"index":33,"secSinceStart":75,"pointDateUnixMilliseconds":1681997511000,"lat":38.00081,"long":23.71338,"speed":23.24605,"speedLimit":50,"speeding":"none","phoneUsage":false},{"index":34,"secSinceStart":76,"pointDateUnixMilliseconds":1681997512000,"lat":38.00078,"long":23.71348,"speed":21.32472,"speedLimit":50,"speeding":"none","phoneUsage":false},{"index":35,"secSinceStart":77,"pointDateUnixMilliseconds":1681997513000,"lat":38.00076,"long":23.71354,"speed":20.08457,"speedLimit":50,"speeding":"none","phoneUsage":false},{"index":36,"secSinceStart":78,"pointDateUnixMilliseconds":1681997514000,"lat":38.00076,"long":23.71354,"speed":19.54111,"speedLimit":50,"speeding":"none","phoneUsage":false},{"index":37,"secSinceStart":79,"pointDateUnixMilliseconds":1681997515000,"lat":38.00072,"long":23.71365,"speed":19.30848,"speedLimit":50,"speeding":"none","phoneUsage":false},{"index":38,"secSinceStart":80,"pointDateUnixMilliseconds":1681997516000,"lat":38.0007,"long":23.71371,"speed":18.96662,"speedLimit":50,"speeding":"none","phoneUsage":false},{"index":39,"secSinceStart":81,"pointDateUnixMilliseconds":1681997517000,"lat":38.0007,"long":23.71371,"speed":17.97594,"speedLimit":50,"speeding":"none","phoneUsage":false},{"index":40,"secSinceStart":82,"pointDateUnixMilliseconds":1681997518000,"lat":38.00067,"long":23.7138,"speed":17.18846,"speedLimit":50,"speeding":"none","phoneUsage":false},{"index":41,"secSinceStart":83,"pointDateUnixMilliseconds":1681997519000,"lat":38.00065,"long":23.71386,"speed":16.24511,"speedLimit":50,"speeding":"none","phoneUsage":false},{"index":42,"secSinceStart":84,"pointDateUnixMilliseconds":1681997520000,"lat":38.00065,"long":23.71386,"speed":15.49732,"speedLimit":50,"speeding":"none","phoneUsage":false},{"index":43,"secSinceStart":85,"pointDateUnixMilliseconds":1681997521000,"lat":38.00062,"long":23.71396,"speed":15.07985,"speedLimit":50,"speeding":"none","phoneUsage":false},{"index":44,"secSinceStart":86,"pointDateUnixMilliseconds":1681997522000,"lat":38.00062,"long":23.71396,"speed":14.89137,"speedLimit":50,"speeding":"none","phoneUsage":false},{"index":45,"secSinceStart":87,"pointDateUnixMilliseconds":1681997523000,"lat":38.00059,"long":23.71403,"speed":14.78865,"speedLimit":50,"speeding":"none","phoneUsage":false},{"index":46,"secSinceStart":88,"pointDateUnixMilliseconds":1681997524000,"lat":38.00059,"long":23.71403,"speed":15.07735,"speedLimit":50,"speeding":"none","phoneUsage":false},{"index":47,"secSinceStart":89,"pointDateUnixMilliseconds":1681997525000,"lat":38.00056,"long":23.71411,"speed":14.97484,"speedLimit":50,"speeding":"none","phoneUsage":false},{"index":48,"secSinceStart":90,"pointDateUnixMilliseconds":1681997526000,"lat":38.00056,"long":23.71411,"speed":15.03981,"speedLimit":50,"speeding":"none","phoneUsage":false},{"index":49,"secSinceStart":91,"pointDateUnixMilliseconds":1681997527000,"lat":38.00052,"long":23.71421,"speed":15.96559,"speedLimit":50,"speeding":"none","phoneUsage":false},{"index":50,"secSinceStart":92,"pointDateUnixMilliseconds":1681997528000,"lat":38.00048,"long":23.7143,"speed":17.41943,"speedLimit":50,"speeding":"none","phoneUsage":false},{"index":51,"secSinceStart":93,"pointDateUnixMilliseconds":1681997529000,"lat":38.00045,"long":23.71438,"speed":18.42746,"speedLimit":50,"speeding":"none","phoneUsage":false},{"index":52,"secSinceStart":94,"pointDateUnixMilliseconds":1681997530000,"lat":38.00045,"long":23.71438,"speed":17.96968,"speedLimit":50,"speeding":"none","phoneUsage":false},{"index":53,"secSinceStart":95,"pointDateUnixMilliseconds":1681997531000,"lat":38.00042,"long":23.71447,"speed":16.70671,"speedLimit":50,"speeding":"none","phoneUsage":false},{"index":54,"secSinceStart":96,"pointDateUnixMilliseconds":1681997532000,"lat":38.00042,"long":23.71447,"speed":15.43574,"speedLimit":50,"speeding":"none","phoneUsage":false},{"index":55,"secSinceStart":97,"pointDateUnixMilliseconds":1681997533000,"lat":38.00037,"long":23.71458,"speed":14.26112,"speedLimit":50,"speeding":"none","phoneUsage":false},{"index":56,"secSinceStart":98,"pointDateUnixMilliseconds":1681997534000,"lat":38.00037,"long":23.71458,"speed":13.33196,"speedLimit":50,"speeding":"none","phoneUsage":false},{"index":57,"secSinceStart":99,"pointDateUnixMilliseconds":1681997535000,"lat":38.00037,"long":23.71458,"speed":12.62263,"speedLimit":50,"speeding":"none","phoneUsage":false},{"index":58,"secSinceStart":100,"pointDateUnixMilliseconds":1681997536000,"lat":38.00036,"long":23.71465,"speed":12.43249,"speedLimit":50,"speeding":"none","phoneUsage":false},{"index":59,"secSinceStart":101,"pointDateUnixMilliseconds":1681997537000,"lat":38.00036,"long":23.71465,"speed":13.09687,"speedLimit":50,"speeding":"none","phoneUsage":false},{"index":60,"secSinceStart":102,"pointDateUnixMilliseconds":1681997538000,"lat":38.00035,"long":23.71474,"speed":13.72152,"speedLimit":50,"speeding":"none","phoneUsage":false},{"index":61,"secSinceStart":103,"pointDateUnixMilliseconds":1681997539000,"lat":38.00034,"long":23.71482,"speed":14.72019,"speedLimit":50,"speeding":"none","phoneUsage":false},{"index":62,"secSinceStart":104,"pointDateUnixMilliseconds":1681997540000,"lat":38.00032,"long":23.71489,"speed":14.81292,"speedLimit":50,"speeding":"none","phoneUsage":false},{"index":63,"secSinceStart":105,"pointDateUnixMilliseconds":1681997541000,"lat":38.00032,"long":23.71489,"speed":14.33783,"speedLimit":50,"speeding":"none","phoneUsage":false},{"index":64,"secSinceStart":106,"pointDateUnixMilliseconds":1681997542000,"lat":38.00031,"long":23.71499,"speed":13.20001,"speedLimit":50,"speeding":"none","phoneUsage":false},{"index":65,"secSinceStart":106,"pointDateUnixMilliseconds":1681997542000,"lat":38.00031,"long":23.71499,"speed":13.20001,"speedLimit":50,"speeding":"none","phoneUsage":false},{"index":66,"secSinceStart":110,"pointDateUnixMilliseconds":1681997546665,"lat":37.99997,"long":23.71506,"speed":13.20001,"speedLimit":50,"speeding":"none","phoneUsage":false},{"index":67,"secSinceStart":118,"pointDateUnixMilliseconds":1681997554000,"lat":37.99963,"long":23.71515,"speed":25.72958,"speedLimit":50,"speeding":"none","phoneUsage":false},{"index":68,"secSinceStart":122,"pointDateUnixMilliseconds":1681997558000,"lat":37.99926,"long":23.71524,"speed":31.53315,"speedLimit":50,"speeding":"none","phoneUsage":false},{"index":69,"secSinceStart":123,"pointDateUnixMilliseconds":1681997559000,"lat":37.99916,"long":23.71527,"speed":32.87233,"speedLimit":50,"speeding":"none","phoneUsage":false},{"index":70,"secSinceStart":124,"pointDateUnixMilliseconds":1681997560000,"lat":37.99906,"long":23.71529,"speed":34.02275,"speedLimit":50,"speeding":"none","phoneUsage":false},{"index":71,"secSinceStart":125,"pointDateUnixMilliseconds":1681997561000,"lat":37.99895,"long":23.71532,"speed":35.06274,"speedLimit":50,"speeding":"none","phoneUsage":false},{"index":72,"secSinceStart":126,"pointDateUnixMilliseconds":1681997562000,"lat":37.99885,"long":23.71535,"speed":35.66632,"speedLimit":50,"speeding":"none","phoneUsage":false},{"index":73,"secSinceStart":127,"pointDateUnixMilliseconds":1681997563000,"lat":37.99875,"long":23.71537,"speed":35.67113,"speedLimit":50,"speeding":"none","phoneUsage":false},{"index":74,"secSinceStart":128,"pointDateUnixMilliseconds":1681997564000,"lat":37.99866,"long":23.7154,"speed":35.66341,"speedLimit":50,"speeding":"none","phoneUsage":false},{"index":75,"secSinceStart":129,"pointDateUnixMilliseconds":1681997565000,"lat":37.99858,"long":23.71542,"speed":35.73226,"speedLimit":50,"speeding":"none","phoneUsage":false},{"index":76,"secSinceStart":130,"pointDateUnixMilliseconds":1681997566000,"lat":37.99848,"long":23.71545,"speed":35.82962,"speedLimit":50,"speeding":"none","phoneUsage":false},{"index":77,"secSinceStart":131,"pointDateUnixMilliseconds":1681997567000,"lat":37.99838,"long":23.71548,"speed":35.94318,"speedLimit":50,"speeding":"none","phoneUsage":false},{"index":78,"secSinceStart":132,"pointDateUnixMilliseconds":1681997568000,"lat":37.99829,"long":23.71551,"speed":36.19781,"speedLimit":50,"speeding":"none","phoneUsage":false},{"index":79,"secSinceStart":133,"pointDateUnixMilliseconds":1681997569000,"lat":37.99819,"long":23.71553,"speed":36.3774,"speedLimit":50,"speeding":"none","phoneUsage":false},{"index":80,"secSinceStart":134,"pointDateUnixMilliseconds":1681997570000,"lat":37.99813,"long":23.71555,"speed":36.69653,"speedLimit":50,"speeding":"none","phoneUsage":false},{"index":81,"secSinceStart":135,"pointDateUnixMilliseconds":1681997571000,"lat":37.99798,"long":23.71558,"speed":37.17291,"speedLimit":50,"speeding":"none","phoneUsage":false},{"index":82,"secSinceStart":136,"pointDateUnixMilliseconds":1681997572000,"lat":37.99788,"long":23.71561,"speed":37.52241,"speedLimit":50,"speeding":"none","phoneUsage":false},{"index":83,"secSinceStart":137,"pointDateUnixMilliseconds":1681997573000,"lat":37.99778,"long":23.71563,"speed":37.73141,"speedLimit":50,"speeding":"none","phoneUsage":false},{"index":84,"secSinceStart":138,"pointDateUnixMilliseconds":1681997574000,"lat":37.99769,"long":23.71565,"speed":37.43264,"speedLimit":50,"speeding":"none","phoneUsage":false},{"index":85,"secSinceStart":139,"pointDateUnixMilliseconds":1681997575000,"lat":37.99762,"long":23.71567,"speed":36.41491,"speedLimit":50,"speeding":"none","phoneUsage":false},{"index":86,"secSinceStart":140,"pointDateUnixMilliseconds":1681997576000,"lat":37.99754,"long":23.71568,"speed":35.09843,"speedLimit":50,"speeding":"none","phoneUsage":false},{"index":87,"secSinceStart":141,"pointDateUnixMilliseconds":1681997577000,"lat":37.99746,"long":23.7157,"speed":33.83315,"speedLimit":50,"speeding":"none","phoneUsage":false},{"index":88,"secSinceStart":144,"pointDateUnixMilliseconds":1681997580000,"lat":37.99729,"long":23.71575,"speed":31.0318,"speedLimit":50,"speeding":"none","phoneUsage":false},{"index":89,"secSinceStart":145,"pointDateUnixMilliseconds":1681997581000,"lat":37.99723,"long":23.71576,"speed":30.27288,"speedLimit":50,"speeding":"none","phoneUsage":false},{"index":90,"secSinceStart":146,"pointDateUnixMilliseconds":1681997582000,"lat":37.99715,"long":23.71578,"speed":29.93086,"speedLimit":50,"speeding":"none","phoneUsage":false},{"index":91,"secSinceStart":148,"pointDateUnixMilliseconds":1681997584173,"lat":37.99696,"long":23.71583,"speed":29.93086,"speedLimit":50,"speeding":"none","phoneUsage":false},{"index":92,"secSinceStart":150,"pointDateUnixMilliseconds":1681997586000,"lat":37.9968,"long":23.71587,"speed":30.13704,"speedLimit":50,"speeding":"none","phoneUsage":false},{"index":93,"secSinceStart":151,"pointDateUnixMilliseconds":1681997587000,"lat":37.99673,"long":23.71589,"speed":30.37128,"speedLimit":0,"speeding":"none","phoneUsage":false},{"index":94,"secSinceStart":152,"pointDateUnixMilliseconds":1681997588000,"lat":37.99665,"long":23.71591,"speed":30.45543,"speedLimit":0,"speeding":"none","phoneUsage":false},{"index":95,"secSinceStart":153,"pointDateUnixMilliseconds":1681997589000,"lat":37.99657,"long":23.71593,"speed":30.1963,"speedLimit":0,"speeding":"none","phoneUsage":false},{"index":96,"secSinceStart":154,"pointDateUnixMilliseconds":1681997590000,"lat":37.9965,"long":23.71595,"speed":29.59423,"speedLimit":0,"speeding":"none","phoneUsage":false},{"index":97,"secSinceStart":155,"pointDateUnixMilliseconds":1681997591000,"lat":37.99643,"long":23.71596,"speed":27.97599,"speedLimit":0,"speeding":"none","phoneUsage":false},{"index":98,"secSinceStart":156,"pointDateUnixMilliseconds":1681997592000,"lat":37.99643,"long":23.71596,"speed":25.2512,"speedLimit":0,"speeding":"none","phoneUsage":false},{"index":99,"secSinceStart":157,"pointDateUnixMilliseconds":1681997593000,"lat":37.99637,"long":23.71598,"speed":22.24106,"speedLimit":0,"speeding":"none","phoneUsage":false},{"index":100,"secSinceStart":158,"pointDateUnixMilliseconds":1681997594000,"lat":37.99637,"long":23.71598,"speed":19.73202,"speedLimit":0,"speeding":"none","phoneUsage":false},{"index":101,"secSinceStart":159,"pointDateUnixMilliseconds":1681997595000,"lat":37.99637,"long":23.71598,"speed":18.30865,"speedLimit":0,"speeding":"none","phoneUsage":false},{"index":102,"secSinceStart":160,"pointDateUnixMilliseconds":1681997596317,"lat":37.99629,"long":23.716,"speed":18.30865,"speedLimit":0,"speeding":"none","phoneUsage":false},{"index":103,"secSinceStart":161,"pointDateUnixMilliseconds":1681997597953,"lat":37.99619,"long":23.71602,"speed":18.30865,"speedLimit":0,"speeding":"none","phoneUsage":false},{"index":104,"secSinceStart":165,"pointDateUnixMilliseconds":1681997601000,"lat":37.99595,"long":23.71608,"speed":23.98968,"speedLimit":50,"speeding":"none","phoneUsage":false},{"index":105,"secSinceStart":166,"pointDateUnixMilliseconds":1681997602000,"lat":37.99587,"long":23.7161,"speed":25.50091,"speedLimit":50,"speeding":"none","phoneUsage":false},{"index":106,"secSinceStart":167,"pointDateUnixMilliseconds":1681997603000,"lat":37.99578,"long":23.71612,"speed":26.86447,"speedLimit":50,"speeding":"none","phoneUsage":false},{"index":107,"secSinceStart":168,"pointDateUnixMilliseconds":1681997604000,"lat":37.9957,"long":23.71615,"speed":27.89684,"speedLimit":50,"speeding":"none","phoneUsage":false},{"index":108,"secSinceStart":168,"pointDateUnixMilliseconds":1681997604253,"lat":37.99564,"long":23.71616,"speed":27.89684,"speedLimit":50,"speeding":"none","phoneUsage":false},{"index":109,"secSinceStart":170,"pointDateUnixMilliseconds":1681997606084,"lat":37.99548,"long":23.71619,"speed":27.89684,"speedLimit":50,"speeding":"none","phoneUsage":false},{"index":110,"secSinceStart":171,"pointDateUnixMilliseconds":1681997607692,"lat":37.99534,"long":23.71622,"speed":27.89684,"speedLimit":50,"speeding":"none","phoneUsage":false},{"index":111,"secSinceStart":173,"pointDateUnixMilliseconds":1681997609077,"lat":37.99522,"long":23.71625,"speed":27.89684,"speedLimit":50,"speeding":"none","phoneUsage":false},{"index":112,"secSinceStart":174,"pointDateUnixMilliseconds":1681997610000,"lat":37.99514,"long":23.71627,"speed":34.89593,"speedLimit":50,"speeding":"none","phoneUsage":false},{"index":113,"secSinceStart":175,"pointDateUnixMilliseconds":1681997611035,"lat":37.99502,"long":23.71631,"speed":34.89593,"speedLimit":50,"speeding":"none","phoneUsage":false},{"index":114,"secSinceStart":175,"pointDateUnixMilliseconds":1681997611035,"lat":37.99502,"long":23.71631,"speed":34.89593,"speedLimit":50,"speeding":"none","phoneUsage":false},{"index":115,"secSinceStart":177,"pointDateUnixMilliseconds":1681997613000,"lat":37.99481,"long":23.71638,"speed":38.4386,"speedLimit":50,"speeding":"none","phoneUsage":false},{"index":116,"secSinceStart":178,"pointDateUnixMilliseconds":1681997614000,"lat":37.99469,"long":23.71642,"speed":39.63943,"speedLimit":50,"speeding":"none","phoneUsage":false},{"index":117,"secSinceStart":179,"pointDateUnixMilliseconds":1681997615000,"lat":37.99454,"long":23.71646,"speed":40.88844,"speedLimit":50,"speeding":"none","phoneUsage":false},{"index":118,"secSinceStart":180,"pointDateUnixMilliseconds":1681997616000,"lat":37.99445,"long":23.71649,"speed":42.002,"speedLimit":50,"speeding":"none","phoneUsage":false},{"index":119,"secSinceStart":181,"pointDateUnixMilliseconds":1681997617000,"lat":37.99433,"long":23.71652,"speed":42.87913,"speedLimit":50,"speeding":"none","phoneUsage":false},{"index":120,"secSinceStart":181,"pointDateUnixMilliseconds":1681997617349,"lat":37.99426,"long":23.71654,"speed":42.87913,"speedLimit":50,"speeding":"none","phoneUsage":false},{"index":121,"secSinceStart":182,"pointDateUnixMilliseconds":1681997618000,"lat":37.99421,"long":23.71655,"speed":43.94001,"speedLimit":50,"speeding":"none","phoneUsage":false},{"index":122,"secSinceStart":183,"pointDateUnixMilliseconds":1681997619000,"lat":37.99411,"long":23.71656,"speed":44.54032,"speedLimit":50,"speeding":"none","phoneUsage":false},{"index":123,"secSinceStart":184,"pointDateUnixMilliseconds":1681997620000,"lat":37.99399,"long":23.71659,"speed":44.73032,"speedLimit":50,"speeding":"none","phoneUsage":false},{"index":124,"secSinceStart":185,"pointDateUnixMilliseconds":1681997621000,"lat":37.99382,"long":23.71664,"speed":44.52218,"speedLimit":50,"speeding":"none","phoneUsage":false},{"index":125,"secSinceStart":186,"pointDateUnixMilliseconds":1681997622000,"lat":37.99375,"long":23.71667,"speed":43.54517,"speedLimit":50,"speeding":"none","phoneUsage":false},{"index":126,"secSinceStart":187,"pointDateUnixMilliseconds":1681997623334,"lat":37.99365,"long":23.7167,"speed":43.54517,"speedLimit":50,"speeding":"none","phoneUsage":false},{"index":127,"secSinceStart":189,"pointDateUnixMilliseconds":1681997625067,"lat":37.99347,"long":23.71675,"speed":43.54517,"speedLimit":50,"speeding":"none","phoneUsage":false},{"index":128,"secSinceStart":189,"pointDateUnixMilliseconds":1681997625067,"lat":37.99347,"long":23.71675,"speed":43.54517,"speedLimit":50,"speeding":"none","phoneUsage":false},{"index":129,"secSinceStart":192,"pointDateUnixMilliseconds":1681997628271,"lat":37.9931,"long":23.71686,"speed":43.54517,"speedLimit":50,"speeding":"none","phoneUsage":false},{"index":130,"secSinceStart":193,"pointDateUnixMilliseconds":1681997629000,"lat":37.99313,"long":23.716920000000002,"speed":32.40501,"speedLimit":50,"speeding":"none","phoneUsage":false},{"index":131,"secSinceStart":194,"pointDateUnixMilliseconds":1681997630000,"lat":37.99313,"long":23.716920000000002,"speed":28.42237,"speedLimit":50,"speeding":"none","phoneUsage":false},{"index":132,"secSinceStart":195,"pointDateUnixMilliseconds":1681997631000,"lat":37.99313,"long":23.716920000000002,"speed":25.4805,"speedLimit":50,"speeding":"none","phoneUsage":false},{"index":133,"secSinceStart":196,"pointDateUnixMilliseconds":1681997632000,"lat":37.99318,"long":23.71703,"speed":24.21858,"speedLimit":50,"speeding":"none","phoneUsage":false},{"index":134,"secSinceStart":197,"pointDateUnixMilliseconds":1681997633000,"lat":37.99322,"long":23.7171,"speed":24.07237,"speedLimit":50,"speeding":"none","phoneUsage":false},{"index":135,"secSinceStart":198,"pointDateUnixMilliseconds":1681997634000,"lat":37.99325,"long":23.71718,"speed":24.37339,"speedLimit":50,"speeding":"none","phoneUsage":false},{"index":136,"secSinceStart":199,"pointDateUnixMilliseconds":1681997635000,"lat":37.99329,"long":23.71726,"speed":24.55055,"speedLimit":50,"speeding":"none","phoneUsage":false},{"index":137,"secSinceStart":200,"pointDateUnixMilliseconds":1681997636000,"lat":37.99335,"long":23.71738,"speed":24.23529,"speedLimit":50,"speeding":"none","phoneUsage":false},{"index":138,"secSinceStart":201,"pointDateUnixMilliseconds":1681997637000,"lat":37.99335,"long":23.71738,"speed":23.18269,"speedLimit":50,"speeding":"none","phoneUsage":false},{"index":139,"secSinceStart":205,"pointDateUnixMilliseconds":1681997641000,"lat":37.99333,"long":23.71766,"speed":21.86778,"speedLimit":50,"speeding":"none","phoneUsage":false},{"index":140,"secSinceStart":208,"pointDateUnixMilliseconds":1681997644000,"lat":37.9933,"long":23.71796,"speed":24.66249,"speedLimit":50,"speeding":"none","phoneUsage":false},{"index":141,"secSinceStart":210,"pointDateUnixMilliseconds":1681997646000,"lat":37.99328,"long":23.71817,"speed":26.84917,"speedLimit":50,"speeding":"none","phoneUsage":false},{"index":142,"secSinceStart":212,"pointDateUnixMilliseconds":1681997648000,"lat":37.99326,"long":23.71843,"speed":29.44578,"speedLimit":50,"speeding":"none","phoneUsage":false},{"index":143,"secSinceStart":212,"pointDateUnixMilliseconds":1681997648000,"lat":37.99326,"long":23.71843,"speed":29.44578,"speedLimit":50,"speeding":"none","phoneUsage":false},{"index":144,"secSinceStart":218,"pointDateUnixMilliseconds":1681997654000,"lat":37.9932,"long":23.71901,"speed":31.14143,"speedLimit":50,"speeding":"none","phoneUsage":false},{"index":145,"secSinceStart":219,"pointDateUnixMilliseconds":1681997655000,"lat":37.99319,"long":23.71915,"speed":31.40749,"speedLimit":50,"speeding":"none","phoneUsage":false},{"index":146,"secSinceStart":220,"pointDateUnixMilliseconds":1681997656000,"lat":37.99318,"long":23.71925,"speed":31.46194,"speedLimit":50,"speeding":"none","phoneUsage":false},{"index":147,"secSinceStart":221,"pointDateUnixMilliseconds":1681997657000,"lat":37.99317,"long":23.71935,"speed":31.43839,"speedLimit":50,"speeding":"none","phoneUsage":false},{"index":148,"secSinceStart":222,"pointDateUnixMilliseconds":1681997658000,"lat":37.99316,"long":23.71945,"speed":31.09042,"speedLimit":50,"speeding":"none","phoneUsage":false},{"index":149,"secSinceStart":223,"pointDateUnixMilliseconds":1681997659000,"lat":37.99315,"long":23.71955,"speed":30.54967,"speedLimit":50,"speeding":"none","phoneUsage":false},{"index":150,"secSinceStart":224,"pointDateUnixMilliseconds":1681997660000,"lat":37.99314,"long":23.71968,"speed":29.04844,"speedLimit":50,"speeding":"none","phoneUsage":false},{"index":151,"secSinceStart":225,"pointDateUnixMilliseconds":1681997661000,"lat":37.99314,"long":23.71968,"speed":26.49349,"speedLimit":50,"speeding":"none","phoneUsage":false},{"index":152,"secSinceStart":228,"pointDateUnixMilliseconds":1681997664081,"lat":37.99314,"long":23.71977,"speed":26.49349,"speedLimit":50,"speeding":"none","phoneUsage":false},{"index":153,"secSinceStart":228,"pointDateUnixMilliseconds":1681997664081,"lat":37.99314,"long":23.71977,"speed":26.49349,"speedLimit":30,"speeding":"none","phoneUsage":false},{"index":154,"secSinceStart":233,"pointDateUnixMilliseconds":1681997669000,"lat":37.99266,"long":23.71955,"speed":25.16868,"speedLimit":30,"speeding":"none","phoneUsage":false},{"index":155,"secSinceStart":236,"pointDateUnixMilliseconds":1681997672000,"lat":37.99242,"long":23.71949,"speed":28.99816,"speedLimit":30,"speeding":"none","phoneUsage":false},{"index":156,"secSinceStart":237,"pointDateUnixMilliseconds":1681997673000,"lat":37.99232,"long":23.71947,"speed":30.46425,"speedLimit":30,"speeding":"none","phoneUsage":false},{"index":157,"secSinceStart":238,"pointDateUnixMilliseconds":1681997674000,"lat":37.99222,"long":23.71944,"speed":31.71651,"speedLimit":30,"speeding":"none","phoneUsage":false},{"index":158,"secSinceStart":239,"pointDateUnixMilliseconds":1681997675000,"lat":37.99213,"long":23.71942,"speed":32.9636,"speedLimit":30,"speeding":"none","phoneUsage":false},{"index":159,"secSinceStart":240,"pointDateUnixMilliseconds":1681997676000,"lat":37.99203,"long":23.71939,"speed":34.21251,"speedLimit":30,"speeding":"none","phoneUsage":false},{"index":160,"secSinceStart":241,"pointDateUnixMilliseconds":1681997677000,"lat":37.99193,"long":23.71937,"speed":35.21687,"speedLimit":30,"speeding":"none","phoneUsage":false},{"index":161,"secSinceStart":242,"pointDateUnixMilliseconds":1681997678000,"lat":37.99183,"long":23.71934,"speed":35.84638,"speedLimit":30,"speeding":"none","phoneUsage":false},{"index":162,"secSinceStart":243,"pointDateUnixMilliseconds":1681997679000,"lat":37.99173,"long":23.71932,"speed":35.61006,"speedLimit":30,"speeding":"none","phoneUsage":false},{"index":163,"secSinceStart":244,"pointDateUnixMilliseconds":1681997680000,"lat":37.99165,"long":23.7193,"speed":34.67599,"speedLimit":30,"speeding":"none","phoneUsage":false},{"index":164,"secSinceStart":245,"pointDateUnixMilliseconds":1681997681000,"lat":37.99158,"long":23.71928,"speed":33.1249,"speedLimit":30,"speeding":"none","phoneUsage":false},{"index":165,"secSinceStart":246,"pointDateUnixMilliseconds":1681997682000,"lat":37.99152,"long":23.71926,"speed":30.52015,"speedLimit":30,"speeding":"none","phoneUsage":false},{"index":166,"secSinceStart":247,"pointDateUnixMilliseconds":1681997683000,"lat":37.99147,"long":23.71925,"speed":27.83243,"speedLimit":30,"speeding":"none","phoneUsage":false},{"index":167,"secSinceStart":248,"pointDateUnixMilliseconds":1681997684000,"lat":37.99142,"long":23.71924,"speed":25.52924,"speedLimit":30,"speeding":"none","phoneUsage":false},{"index":168,"secSinceStart":249,"pointDateUnixMilliseconds":1681997685000,"lat":37.99137,"long":23.71928,"speed":23.50007,"speedLimit":50,"speeding":"none","phoneUsage":false},{"index":169,"secSinceStart":250,"pointDateUnixMilliseconds":1681997686000,"lat":37.99132,"long":23.71931,"speed":22.79148,"speedLimit":50,"speeding":"none","phoneUsage":false},{"index":170,"secSinceStart":251,"pointDateUnixMilliseconds":1681997687000,"lat":37.99127,"long":23.71935,"speed":22.95828,"speedLimit":50,"speeding":"none","phoneUsage":false},{"index":171,"secSinceStart":252,"pointDateUnixMilliseconds":1681997688165,"lat":37.9912,"long":23.7194,"speed":22.95828,"speedLimit":50,"speeding":"none","phoneUsage":false},{"index":172,"secSinceStart":256,"pointDateUnixMilliseconds":1681997692000,"lat":37.99096,"long":23.71954,"speed":26.21632,"speedLimit":50,"speeding":"none","phoneUsage":false},{"index":173,"secSinceStart":257,"pointDateUnixMilliseconds":1681997693000,"lat":37.99087,"long":23.71954,"speed":27.57222,"speedLimit":50,"speeding":"none","phoneUsage":false},{"index":174,"secSinceStart":259,"pointDateUnixMilliseconds":1681997695000,"lat":37.99068,"long":23.71955,"speed":30.48118,"speedLimit":50,"speeding":"none","phoneUsage":false},{"index":175,"secSinceStart":260,"pointDateUnixMilliseconds":1681997696101,"lat":37.99057,"long":23.71956,"speed":30.48118,"speedLimit":50,"speeding":"none","phoneUsage":false},{"index":176,"secSinceStart":261,"pointDateUnixMilliseconds":1681997697000,"lat":37.99048,"long":23.71956,"speed":32.77198,"speedLimit":50,"speeding":"none","phoneUsage":false},{"index":177,"secSinceStart":264,"pointDateUnixMilliseconds":1681997700000,"lat":37.99018,"long":23.71955,"speed":36.16014,"speedLimit":50,"speeding":"none","phoneUsage":false},{"index":178,"secSinceStart":264,"pointDateUnixMilliseconds":1681997700566,"lat":37.99012,"long":23.71955,"speed":36.16014,"speedLimit":50,"speeding":"none","phoneUsage":false},{"index":179,"secSinceStart":266,"pointDateUnixMilliseconds":1681997702000,"lat":37.98997,"long":23.71952,"speed":38.24258,"speedLimit":50,"speeding":"none","phoneUsage":false},{"index":180,"secSinceStart":267,"pointDateUnixMilliseconds":1681997703000,"lat":37.98987,"long":23.71951,"speed":38.95752,"speedLimit":50,"speeding":"none","phoneUsage":false},{"index":181,"secSinceStart":268,"pointDateUnixMilliseconds":1681997704000,"lat":37.98976,"long":23.71949,"speed":39.62542,"speedLimit":50,"speeding":"none","phoneUsage":false},{"index":182,"secSinceStart":269,"pointDateUnixMilliseconds":1681997705301,"lat":37.98961,"long":23.71946,"speed":39.62542,"speedLimit":50,"speeding":"none","phoneUsage":false},{"index":183,"secSinceStart":270,"pointDateUnixMilliseconds":1681997706000,"lat":37.98953,"long":23.71944,"speed":41.18678,"speedLimit":50,"speeding":"none","phoneUsage":false},{"index":184,"secSinceStart":272,"pointDateUnixMilliseconds":1681997708088,"lat":37.98929,"long":23.71937,"speed":41.18678,"speedLimit":50,"speeding":"none","phoneUsage":false},{"index":185,"secSinceStart":273,"pointDateUnixMilliseconds":1681997709000,"lat":37.98919,"long":23.71932,"speed":43.45329,"speedLimit":50,"speeding":"none","phoneUsage":false},{"index":186,"secSinceStart":276,"pointDateUnixMilliseconds":1681997712943,"lat":37.98874,"long":23.71909,"speed":43.45329,"speedLimit":50,"speeding":"none","phoneUsage":false},{"index":187,"secSinceStart":278,"pointDateUnixMilliseconds":1681997714000,"lat":37.98861,"long":23.71909,"speed":44.58302,"speedLimit":50,"speeding":"none","phoneUsage":false},{"index":188,"secSinceStart":279,"pointDateUnixMilliseconds":1681997715000,"lat":37.9885,"long":23.71908,"speed":43.74104,"speedLimit":50,"speeding":"none","phoneUsage":false},{"index":189,"secSinceStart":279,"pointDateUnixMilliseconds":1681997715472,"lat":37.98845,"long":23.71908,"speed":43.74104,"speedLimit":50,"speeding":"none","phoneUsage":false},{"index":190,"secSinceStart":280,"pointDateUnixMilliseconds":1681997716000,"lat":37.98838,"long":23.71909,"speed":42.45952,"speedLimit":50,"speeding":"none","phoneUsage":false},{"index":191,"secSinceStart":281,"pointDateUnixMilliseconds":1681997717000,"lat":37.98829,"long":23.71911,"speed":40.9074,"speedLimit":50,"speeding":"none","phoneUsage":false},{"index":192,"secSinceStart":282,"pointDateUnixMilliseconds":1681997718000,"lat":37.98821,"long":23.71912,"speed":39.22377,"speedLimit":50,"speeding":"none","phoneUsage":false},{"index":193,"secSinceStart":283,"pointDateUnixMilliseconds":1681997719000,"lat":37.98813,"long":23.71914,"speed":37.2722,"speedLimit":50,"speeding":"none","phoneUsage":false},{"index":194,"secSinceStart":284,"pointDateUnixMilliseconds":1681997720000,"lat":37.98806,"long":23.71916,"speed":35.22982,"speedLimit":50,"speeding":"none","phoneUsage":false},{"index":195,"secSinceStart":285,"pointDateUnixMilliseconds":1681997721000,"lat":37.98797,"long":23.71922,"speed":32.81233,"speedLimit":50,"speeding":"none","phoneUsage":false},{"index":196,"secSinceStart":286,"pointDateUnixMilliseconds":1681997722000,"lat":37.98793,"long":23.71925,"speed":29.88747,"speedLimit":50,"speeding":"none","phoneUsage":false},{"index":197,"secSinceStart":287,"pointDateUnixMilliseconds":1681997723000,"lat":37.98789,"long":23.71928,"speed":26.69046,"speedLimit":50,"speeding":"none","phoneUsage":false},{"index":198,"secSinceStart":288,"pointDateUnixMilliseconds":1681997724000,"lat":37.98789,"long":23.71928,"speed":23.39433,"speedLimit":50,"speeding":"none","phoneUsage":false},{"index":199,"secSinceStart":289,"pointDateUnixMilliseconds":1681997725000,"lat":37.98784,"long":23.71931,"speed":20.36083,"speedLimit":50,"speeding":"none","phoneUsage":false},{"index":200,"secSinceStart":295,"pointDateUnixMilliseconds":1681997731000,"lat":37.98784,"long":23.71931,"speed":5.36907,"speedLimit":50,"speeding":"none","phoneUsage":false},{"index":201,"secSinceStart":301,"pointDateUnixMilliseconds":1681997737000,"lat":37.98784,"long":23.71931,"speed":1.41748,"speedLimit":50,"speeding":"none","phoneUsage":false},{"index":202,"secSinceStart":307,"pointDateUnixMilliseconds":1681997743000,"lat":37.98784,"long":23.71931,"speed":0.42696,"speedLimit":50,"speeding":"none","phoneUsage":false},{"index":203,"secSinceStart":313,"pointDateUnixMilliseconds":1681997749000,"lat":37.98784,"long":23.71931,"speed":0.19558,"speedLimit":50,"speeding":"none","phoneUsage":false},{"index":204,"secSinceStart":321,"pointDateUnixMilliseconds":1681997757000,"lat":37.98784,"long":23.71931,"speed":1.73799,"speedLimit":50,"speeding":"none","phoneUsage":false},{"index":205,"secSinceStart":323,"pointDateUnixMilliseconds":1681997759000,"lat":37.98778,"long":23.71935,"speed":4.42831,"speedLimit":50,"speeding":"none","phoneUsage":false},{"index":206,"secSinceStart":323,"pointDateUnixMilliseconds":1681997759622,"lat":37.98768,"long":23.71942,"speed":4.42831,"speedLimit":50,"speeding":"none","phoneUsage":false},{"index":207,"secSinceStart":324,"pointDateUnixMilliseconds":1681997760065,"lat":37.9876,"long":23.71944,"speed":4.42831,"speedLimit":50,"speeding":"none","phoneUsage":false},{"index":208,"secSinceStart":324,"pointDateUnixMilliseconds":1681997760883,"lat":37.9876,"long":23.71963,"speed":4.42831,"speedLimit":50,"speeding":"none","phoneUsage":false},{"index":209,"secSinceStart":326,"pointDateUnixMilliseconds":1681997762907,"lat":37.98761,"long":23.7201,"speed":4.42831,"speedLimit":50,"speeding":"none","phoneUsage":false},{"index":210,"secSinceStart":327,"pointDateUnixMilliseconds":1681997763596,"lat":37.98761,"long":23.72026,"speed":4.42831,"speedLimit":50,"speeding":"none","phoneUsage":false},{"index":211,"secSinceStart":328,"pointDateUnixMilliseconds":1681997764149,"lat":37.9877,"long":23.7202,"speed":4.42831,"speedLimit":50,"speeding":"none","phoneUsage":false},{"index":212,"secSinceStart":329,"pointDateUnixMilliseconds":1681997765000,"lat":37.98783,"long":23.72009,"speed":14.26313,"speedLimit":50,"speeding":"none","phoneUsage":false},{"index":213,"secSinceStart":335,"pointDateUnixMilliseconds":1681997771000,"lat":37.98791,"long":23.72004,"speed":14.78345,"speedLimit":50,"speeding":"none","phoneUsage":false},{"index":214,"secSinceStart":336,"pointDateUnixMilliseconds":1681997772459,"lat":37.988,"long":23.71999,"speed":14.78345,"speedLimit":50,"speeding":"none","phoneUsage":false},{"index":215,"secSinceStart":337,"pointDateUnixMilliseconds":1681997773555,"lat":37.98807,"long":23.71996,"speed":14.78345,"speedLimit":50,"speeding":"none","phoneUsage":false},{"index":216,"secSinceStart":338,"pointDateUnixMilliseconds":1681997774621,"lat":37.98814,"long":23.71994,"speed":14.78345,"speedLimit":50,"speeding":"none","phoneUsage":false},{"index":217,"secSinceStart":339,"pointDateUnixMilliseconds":1681997775807,"lat":37.98822,"long":23.71994,"speed":14.78345,"speedLimit":50,"speeding":"none","phoneUsage":false},{"index":218,"secSinceStart":341,"pointDateUnixMilliseconds":1681997777000,"lat":37.9883,"long":23.71995,"speed":21.48199,"speedLimit":50,"speeding":"none","phoneUsage":false},{"index":219,"secSinceStart":342,"pointDateUnixMilliseconds":1681997778746,"lat":37.98839,"long":23.71997,"speed":21.48199,"speedLimit":50,"speeding":"none","phoneUsage":false},{"index":220,"secSinceStart":348,"pointDateUnixMilliseconds":1681997784762,"lat":37.9887,"long":23.72004,"speed":21.48199,"speedLimit":50,"speeding":"none","phoneUsage":false},{"index":221,"secSinceStart":347,"pointDateUnixMilliseconds":1681997783000,"lat":37.98869,"long":23.72012,"speed":25.21265,"speedLimit":50,"speeding":"none","phoneUsage":false},{"index":222,"secSinceStart":353,"pointDateUnixMilliseconds":1681997789000,"lat":37.98863,"long":23.72059,"speed":22.8272,"speedLimit":50,"speeding":"none","phoneUsage":false},{"index":223,"secSinceStart":359,"pointDateUnixMilliseconds":1681997795000,"lat":37.98857,"long":23.72099,"speed":17.91209,"speedLimit":50,"speeding":"none","phoneUsage":false},{"index":224,"secSinceStart":362,"pointDateUnixMilliseconds":1681997798592,"lat":37.98842,"long":23.72095,"speed":17.91209,"speedLimit":50,"speeding":"none","phoneUsage":false},{"index":225,"secSinceStart":365,"pointDateUnixMilliseconds":1681997801000,"lat":37.98832,"long":23.72092,"speed":14.69991,"speedLimit":50,"speeding":"none","phoneUsage":false},{"index":226,"secSinceStart":369,"pointDateUnixMilliseconds":1681997805921,"lat":37.988,"long":23.72084,"speed":14.69991,"speedLimit":50,"speeding":"none","phoneUsage":false},{"index":227,"secSinceStart":371,"pointDateUnixMilliseconds":1681997807000,"lat":37.98793,"long":23.72082,"speed":18.62802,"speedLimit":50,"speeding":"none","phoneUsage":false},{"index":228,"secSinceStart":375,"pointDateUnixMilliseconds":1681997811000,"lat":37.98774,"long":23.72077,"speed":16.90149,"speedLimit":50,"speeding":"none","phoneUsage":false}],"events":[{"id":"","type":"Braking","date":"2023-04-20T16:31:50+03:00","lat":38.00081,"long":23.71338,"value":-3.5066885948181152,"confirmNeeded":null,"asI15":null}],"related":[{"type":"Waypoints","uri":"https://api.telematicssdk.com/trips/get/admin/v1/873ca763-0473-4010-a863-0fd0bbd678af/waypoints"}]}}