{"trip":{"id":"720cf724-fdbe-44d0-b29f-ac5bb71d31b5","dateUpdated":"2023-04-17T10:27:25+00:00","identifiers":{"companyId":"8a71134c-9b55-48fd-a5ee-fec5f0181192","applicationId":"75f84ece-7c8a-4b69-b5d6-307bb473c6a7","instanceId":"b7003815-6d34-4963-8731-e58f1b7a7748","userId":"6b6170d0-8bb2-46de-8125-feb9f95388b2"},"data":{"startDate":"2023-04-17T13:12:11+03:00","startDateUnixMilliseconds":1681726331000,"endDate":"2023-04-17T13:20:20+03:00","endDateUnixMilliseconds":1681726820000,"unitSystem":0,"addresses":{"start":{"full":"Fist Boxing Gym &Mma, Εθνική Οδός Παλαιοκαστρίτσης, 491 32 Corfu, Greece","parts":{"countryCode":"GRC","country":"Greece","county":"Corfu","state":"Ionia Nisia","city":"Corfu","district":"Corfu","street":"Εθνική Οδός Παλαιοκαστρίτσης","house":null}},"end":{"full":"Spiteri Toni P., 491 00 Corfu, Greece","parts":{"countryCode":"GRC","country":"Greece","county":"Corfu","state":"Ionia Nisia","city":"Corfu","district":"Corfu","street":"Spiteri Toni P.","house":null}}},"transportType":{"current":"OriginalDriver","confirmNeeded":false},"tags":[],"vehicle":null},"statistics":{"mileage":1.9320582359407767,"durationMinutes":8.15,"accelerationsCount":0,"brakingsCount":0,"corneringsCount":0,"totalSpeedingMileage":0,"midSpeedingMileage":0,"highSpeedingMileage":0,"phoneUsageDurationMinutes":0,"phoneUsageMileage":0,"phoneUsageWithSpeedingDurationMinutes":0,"phoneUsageWithSpeedingMileage":0,"accidentsCount":null,"dayHours":8.157583236694336,"rushHours":0,"nightHours":0,"averageSpeed":20.629626611099,"maxSpeed":32.29494857788086},"scores":{"safety":100,"acceleration":100,"braking":100,"cornering":100,"speeding":100,"phoneUsage":100,"eco":100,"ecoBrakes":100,"ecoDepreciation":100,"ecoFuel":100,"ecoTyres":100},"waypoints":[{"index":0,"secSinceStart":0,"pointDateUnixMilliseconds":1681726331000,"lat":39.62217,"long":19.90839,"speed":0,"speedLimit":40,"speeding":"none","phoneUsage":false},{"index":1,"secSinceStart":0,"pointDateUnixMilliseconds":1681726331975,"lat":39.62211,"long":19.90828,"speed":1.35218,"speedLimit":40,"speeding":"none","phoneUsage":false},{"index":2,"secSinceStart":2,"pointDateUnixMilliseconds":1681726333754,"lat":39.62199,"long":19.90809,"speed":3.81938,"speedLimit":40,"speeding":"none","phoneUsage":false},{"index":3,"secSinceStart":3,"pointDateUnixMilliseconds":1681726334615,"lat":39.62193,"long":19.908,"speed":5.01345,"speedLimit":40,"speeding":"none","phoneUsage":false},{"index":4,"secSinceStart":4,"pointDateUnixMilliseconds":1681726335353,"lat":39.62188,"long":19.90792,"speed":6.03695,"speedLimit":30,"speeding":"none","phoneUsage":false},{"index":5,"secSinceStart":6,"pointDateUnixMilliseconds":1681726337000,"lat":39.62177,"long":19.90774,"speed":8.32109,"speedLimit":30,"speeding":"none","phoneUsage":false},{"index":6,"secSinceStart":6,"pointDateUnixMilliseconds":1681726337847,"lat":39.62172,"long":19.90765,"speed":9.49575,"speedLimit":30,"speeding":"none","phoneUsage":false},{"index":7,"secSinceStart":8,"pointDateUnixMilliseconds":1681726339723,"lat":39.62161,"long":19.90745,"speed":12.09747,"speedLimit":30,"speeding":"none","phoneUsage":false},{"index":8,"secSinceStart":10,"pointDateUnixMilliseconds":1681726341726,"lat":39.6215,"long":19.90723,"speed":14.87533,"speedLimit":30,"speeding":"none","phoneUsage":false},{"index":9,"secSinceStart":12,"pointDateUnixMilliseconds":1681726343000,"lat":39.62143,"long":19.90709,"speed":16.64217,"speedLimit":30,"speeding":"none","phoneUsage":false},{"index":10,"secSinceStart":14,"pointDateUnixMilliseconds":1681726345577,"lat":39.62132,"long":19.90686,"speed":20.21608,"speedLimit":30,"speeding":"none","phoneUsage":false},{"index":11,"secSinceStart":18,"pointDateUnixMilliseconds":1681726349000,"lat":39.62118,"long":19.90655,"speed":24.96326,"speedLimit":40,"speeding":"none","phoneUsage":false},{"index":12,"secSinceStart":19,"pointDateUnixMilliseconds":1681726350486,"lat":39.62112,"long":19.90642,"speed":27.02411,"speedLimit":40,"speeding":"none","phoneUsage":false},{"index":13,"secSinceStart":20,"pointDateUnixMilliseconds":1681726351971,"lat":39.62106,"long":19.90629,"speed":29.08358,"speedLimit":40,"speeding":"none","phoneUsage":false},{"index":14,"secSinceStart":22,"pointDateUnixMilliseconds":1681726353628,"lat":39.621,"long":19.90614,"speed":31.38159,"speedLimit":40,"speeding":"none","phoneUsage":false},{"index":15,"secSinceStart":24,"pointDateUnixMilliseconds":1681726355000,"lat":39.62096,"long":19.90601,"speed":29.3869,"speedLimit":40,"speeding":"none","phoneUsage":false},{"index":16,"secSinceStart":25,"pointDateUnixMilliseconds":1681726356420,"lat":39.62093,"long":19.90589,"speed":29.3869,"speedLimit":40,"speeding":"none","phoneUsage":false},{"index":17,"secSinceStart":26,"pointDateUnixMilliseconds":1681726357474,"lat":39.62091,"long":19.9058,"speed":29.3869,"speedLimit":40,"speeding":"none","phoneUsage":false},{"index":18,"secSinceStart":27,"pointDateUnixMilliseconds":1681726358055,"lat":39.6209,"long":19.90575,"speed":29.3869,"speedLimit":40,"speeding":"none","phoneUsage":false},{"index":19,"secSinceStart":27,"pointDateUnixMilliseconds":1681726358967,"lat":39.62089,"long":19.90567,"speed":29.3869,"speedLimit":40,"speeding":"none","phoneUsage":false},{"index":20,"secSinceStart":29,"pointDateUnixMilliseconds":1681726360325,"lat":39.62088,"long":19.90555,"speed":29.3869,"speedLimit":40,"speeding":"none","phoneUsage":false},{"index":21,"secSinceStart":30,"pointDateUnixMilliseconds":1681726361000,"lat":39.62088,"long":19.90549,"speed":30.15234,"speedLimit":40,"speeding":"none","phoneUsage":false},{"index":22,"secSinceStart":32,"pointDateUnixMilliseconds":1681726363099,"lat":39.62089,"long":19.90533,"speed":30.15234,"speedLimit":40,"speeding":"none","phoneUsage":false},{"index":23,"secSinceStart":33,"pointDateUnixMilliseconds":1681726364548,"lat":39.6209,"long":19.90522,"speed":30.15234,"speedLimit":40,"speeding":"none","phoneUsage":false},{"index":24,"secSinceStart":34,"pointDateUnixMilliseconds":1681726365350,"lat":39.62091,"long":19.90516,"speed":30.15234,"speedLimit":40,"speeding":"none","phoneUsage":false},{"index":25,"secSinceStart":36,"pointDateUnixMilliseconds":1681726367000,"lat":39.62094,"long":19.90504,"speed":30.96116,"speedLimit":40,"speeding":"none","phoneUsage":false},{"index":26,"secSinceStart":42,"pointDateUnixMilliseconds":1681726373000,"lat":39.62112,"long":19.90461,"speed":24.79322,"speedLimit":40,"speeding":"none","phoneUsage":false},{"index":27,"secSinceStart":55,"pointDateUnixMilliseconds":1681726386000,"lat":39.62112,"long":19.90461,"speed":11.9636,"speedLimit":40,"speeding":"none","phoneUsage":false},{"index":28,"secSinceStart":61,"pointDateUnixMilliseconds":1681726392000,"lat":39.62112,"long":19.90461,"speed":9.65442,"speedLimit":40,"speeding":"none","phoneUsage":false},{"index":29,"secSinceStart":67,"pointDateUnixMilliseconds":1681726398000,"lat":39.62112,"long":19.90461,"speed":7.91855,"speedLimit":40,"speeding":"none","phoneUsage":false},{"index":30,"secSinceStart":77,"pointDateUnixMilliseconds":1681726408000,"lat":39.62112,"long":19.90461,"speed":7.65032,"speedLimit":40,"speeding":"none","phoneUsage":false},{"index":31,"secSinceStart":83,"pointDateUnixMilliseconds":1681726414000,"lat":39.62107,"long":19.90454,"speed":12.25666,"speedLimit":50,"speeding":"none","phoneUsage":false},{"index":32,"secSinceStart":84,"pointDateUnixMilliseconds":1681726415000,"lat":39.62102,"long":19.90448,"speed":13.52609,"speedLimit":50,"speeding":"none","phoneUsage":false},{"index":33,"secSinceStart":85,"pointDateUnixMilliseconds":1681726416000,"lat":39.62095,"long":19.9044,"speed":15.04057,"speedLimit":50,"speeding":"none","phoneUsage":false},{"index":34,"secSinceStart":86,"pointDateUnixMilliseconds":1681726417000,"lat":39.62089,"long":19.90431,"speed":16.64579,"speedLimit":50,"speeding":"none","phoneUsage":false},{"index":35,"secSinceStart":87,"pointDateUnixMilliseconds":1681726418000,"lat":39.62083,"long":19.90422,"speed":18.34585,"speedLimit":50,"speeding":"none","phoneUsage":false},{"index":36,"secSinceStart":87,"pointDateUnixMilliseconds":1681726418845,"lat":39.62078,"long":19.90413,"speed":18.34585,"speedLimit":50,"speeding":"none","phoneUsage":false},{"index":37,"secSinceStart":89,"pointDateUnixMilliseconds":1681726420000,"lat":39.62072,"long":19.904,"speed":21.85399,"speedLimit":50,"speeding":"none","phoneUsage":false},{"index":38,"secSinceStart":90,"pointDateUnixMilliseconds":1681726421000,"lat":39.62068,"long":19.90392,"speed":23.14989,"speedLimit":50,"speeding":"none","phoneUsage":false},{"index":39,"secSinceStart":91,"pointDateUnixMilliseconds":1681726422000,"lat":39.62063,"long":19.90382,"speed":24.39559,"speedLimit":50,"speeding":"none","phoneUsage":false},{"index":40,"secSinceStart":95,"pointDateUnixMilliseconds":1681726426000,"lat":39.62043,"long":19.90341,"speed":28.89606,"speedLimit":50,"speeding":"none","phoneUsage":false},{"index":41,"secSinceStart":101,"pointDateUnixMilliseconds":1681726432455,"lat":39.62016,"long":19.90286,"speed":28.89606,"speedLimit":50,"speeding":"none","phoneUsage":false},{"index":42,"secSinceStart":101,"pointDateUnixMilliseconds":1681726432000,"lat":39.62009,"long":19.90272,"speed":33.91786,"speedLimit":50,"speeding":"none","phoneUsage":false},{"index":43,"secSinceStart":104,"pointDateUnixMilliseconds":1681726435000,"lat":39.61994,"long":19.9024,"speed":34.49593,"speedLimit":50,"speeding":"none","phoneUsage":false},{"index":44,"secSinceStart":105,"pointDateUnixMilliseconds":1681726436000,"lat":39.61989,"long":19.90228,"speed":33.83395,"speedLimit":50,"speeding":"none","phoneUsage":false},{"index":45,"secSinceStart":105,"pointDateUnixMilliseconds":1681726436990,"lat":39.61986,"long":19.90221,"speed":33.83395,"speedLimit":50,"speeding":"none","phoneUsage":false},{"index":46,"secSinceStart":107,"pointDateUnixMilliseconds":1681726438000,"lat":39.61981,"long":19.9021,"speed":33.04415,"speedLimit":50,"speeding":"none","phoneUsage":false},{"index":47,"secSinceStart":108,"pointDateUnixMilliseconds":1681726439000,"lat":39.61978,"long":19.90202,"speed":32.5546,"speedLimit":50,"speeding":"none","phoneUsage":false},{"index":48,"secSinceStart":109,"pointDateUnixMilliseconds":1681726440000,"lat":39.61975,"long":19.9019,"speed":32.31305,"speedLimit":50,"speeding":"none","phoneUsage":false},{"index":49,"secSinceStart":110,"pointDateUnixMilliseconds":1681726441000,"lat":39.61973,"long":19.9018,"speed":32.22883,"speedLimit":50,"speeding":"none","phoneUsage":false},{"index":50,"secSinceStart":111,"pointDateUnixMilliseconds":1681726442000,"lat":39.61971,"long":19.90169,"speed":32.08181,"speedLimit":50,"speeding":"none","phoneUsage":false},{"index":51,"secSinceStart":113,"pointDateUnixMilliseconds":1681726444000,"lat":39.61966,"long":19.90148,"speed":31.43815,"speedLimit":50,"speeding":"none","phoneUsage":false},{"index":52,"secSinceStart":114,"pointDateUnixMilliseconds":1681726445000,"lat":39.61964,"long":19.90138,"speed":31.17313,"speedLimit":50,"speeding":"none","phoneUsage":false},{"index":53,"secSinceStart":115,"pointDateUnixMilliseconds":1681726446000,"lat":39.61962,"long":19.9013,"speed":30.92528,"speedLimit":50,"speeding":"none","phoneUsage":false},{"index":54,"secSinceStart":116,"pointDateUnixMilliseconds":1681726447000,"lat":39.61959,"long":19.90114,"speed":30.71817,"speedLimit":50,"speeding":"none","phoneUsage":false},{"index":55,"secSinceStart":117,"pointDateUnixMilliseconds":1681726448459,"lat":39.61957,"long":19.90099,"speed":30.71817,"speedLimit":50,"speeding":"none","phoneUsage":false},{"index":56,"secSinceStart":119,"pointDateUnixMilliseconds":1681726450000,"lat":39.61955,"long":19.90085,"speed":29.85441,"speedLimit":50,"speeding":"none","phoneUsage":false},{"index":57,"secSinceStart":120,"pointDateUnixMilliseconds":1681726451000,"lat":39.61954,"long":19.90076,"speed":29.55289,"speedLimit":50,"speeding":"none","phoneUsage":false},{"index":58,"secSinceStart":121,"pointDateUnixMilliseconds":1681726452000,"lat":39.61953,"long":19.90065,"speed":29.61213,"speedLimit":50,"speeding":"none","phoneUsage":false},{"index":59,"secSinceStart":122,"pointDateUnixMilliseconds":1681726453000,"lat":39.61952,"long":19.90054,"speed":30.03381,"speedLimit":50,"speeding":"none","phoneUsage":false},{"index":60,"secSinceStart":125,"pointDateUnixMilliseconds":1681726456000,"lat":39.6195,"long":19.90027,"speed":30.56597,"speedLimit":50,"speeding":"none","phoneUsage":false},{"index":61,"secSinceStart":126,"pointDateUnixMilliseconds":1681726457000,"lat":39.61949,"long":19.90014,"speed":30.29738,"speedLimit":50,"speeding":"none","phoneUsage":false},{"index":62,"secSinceStart":127,"pointDateUnixMilliseconds":1681726458844,"lat":39.61947,"long":19.89997,"speed":30.29738,"speedLimit":50,"speeding":"none","phoneUsage":false},{"index":63,"secSinceStart":131,"pointDateUnixMilliseconds":1681726462000,"lat":39.6194,"long":19.89969,"speed":31.28672,"speedLimit":50,"speeding":"none","phoneUsage":false},{"index":64,"secSinceStart":132,"pointDateUnixMilliseconds":1681726463000,"lat":39.6194,"long":19.89951,"speed":31.1572,"speedLimit":50,"speeding":"none","phoneUsage":false},{"index":65,"secSinceStart":133,"pointDateUnixMilliseconds":1681726464000,"lat":39.6194,"long":19.89951,"speed":30.71262,"speedLimit":50,"speeding":"none","phoneUsage":false},{"index":66,"secSinceStart":134,"pointDateUnixMilliseconds":1681726465000,"lat":39.61942,"long":19.89944,"speed":29.62637,"speedLimit":50,"speeding":"none","phoneUsage":false},{"index":67,"secSinceStart":135,"pointDateUnixMilliseconds":1681726466000,"lat":39.61944,"long":19.89936,"speed":29.60569,"speedLimit":50,"speeding":"none","phoneUsage":false},{"index":68,"secSinceStart":136,"pointDateUnixMilliseconds":1681726467000,"lat":39.6195,"long":19.89921,"speed":29.7145,"speedLimit":50,"speeding":"none","phoneUsage":false},{"index":69,"secSinceStart":137,"pointDateUnixMilliseconds":1681726468000,"lat":39.61955,"long":19.89909,"speed":30.46583,"speedLimit":50,"speeding":"none","phoneUsage":false},{"index":70,"secSinceStart":138,"pointDateUnixMilliseconds":1681726469000,"lat":39.61961,"long":19.89895,"speed":31.42139,"speedLimit":50,"speeding":"none","phoneUsage":false},{"index":71,"secSinceStart":139,"pointDateUnixMilliseconds":1681726470000,"lat":39.61965,"long":19.89884,"speed":32.29495,"speedLimit":50,"speeding":"none","phoneUsage":false},{"index":72,"secSinceStart":140,"pointDateUnixMilliseconds":1681726471368,"lat":39.61968,"long":19.89874,"speed":32.29495,"speedLimit":50,"speeding":"none","phoneUsage":false},{"index":73,"secSinceStart":144,"pointDateUnixMilliseconds":1681726475000,"lat":39.61972,"long":19.89846,"speed":29.42336,"speedLimit":50,"speeding":"none","phoneUsage":false},{"index":74,"secSinceStart":145,"pointDateUnixMilliseconds":1681726476000,"lat":39.61973,"long":19.89837,"speed":28.54434,"speedLimit":50,"speeding":"none","phoneUsage":false},{"index":75,"secSinceStart":146,"pointDateUnixMilliseconds":1681726477882,"lat":39.61974,"long":19.89828,"speed":28.54434,"speedLimit":50,"speeding":"none","phoneUsage":false},{"index":76,"secSinceStart":149,"pointDateUnixMilliseconds":1681726480692,"lat":39.61971,"long":19.89815,"speed":28.54434,"speedLimit":50,"speeding":"none","phoneUsage":false},{"index":77,"secSinceStart":151,"pointDateUnixMilliseconds":1681726482000,"lat":39.61968,"long":19.8981,"speed":24.74265,"speedLimit":50,"speeding":"none","phoneUsage":false},{"index":78,"secSinceStart":153,"pointDateUnixMilliseconds":1681726484000,"lat":39.61959,"long":19.89798,"speed":24.82289,"speedLimit":50,"speeding":"none","phoneUsage":false},{"index":79,"secSinceStart":156,"pointDateUnixMilliseconds":1681726487715,"lat":39.61945,"long":19.89777,"speed":24.82289,"speedLimit":50,"speeding":"none","phoneUsage":false},{"index":80,"secSinceStart":159,"pointDateUnixMilliseconds":1681726490000,"lat":39.61933,"long":19.8977,"speed":26.12444,"speedLimit":50,"speeding":"none","phoneUsage":false},{"index":81,"secSinceStart":162,"pointDateUnixMilliseconds":1681726493000,"lat":39.61911,"long":19.89771,"speed":27.29249,"speedLimit":50,"speeding":"none","phoneUsage":false},{"index":82,"secSinceStart":163,"pointDateUnixMilliseconds":1681726494000,"lat":39.619,"long":19.89773,"speed":28.51774,"speedLimit":50,"speeding":"none","phoneUsage":false},{"index":83,"secSinceStart":163,"pointDateUnixMilliseconds":1681726494351,"lat":39.61894,"long":19.89778,"speed":28.51774,"speedLimit":50,"speeding":"none","phoneUsage":false},{"index":84,"secSinceStart":164,"pointDateUnixMilliseconds":1681726495000,"lat":39.61881,"long":19.89775,"speed":29.51732,"speedLimit":50,"speeding":"none","phoneUsage":false},{"index":85,"secSinceStart":165,"pointDateUnixMilliseconds":1681726496000,"lat":39.61875,"long":19.89773,"speed":30.08435,"speedLimit":50,"speeding":"none","phoneUsage":false},{"index":86,"secSinceStart":165,"pointDateUnixMilliseconds":1681726496238,"lat":39.61868,"long":19.89771,"speed":30.08435,"speedLimit":50,"speeding":"none","phoneUsage":false},{"index":87,"secSinceStart":165,"pointDateUnixMilliseconds":1681726496614,"lat":39.61859,"long":19.89762,"speed":30.08435,"speedLimit":50,"speeding":"none","phoneUsage":false},{"index":88,"secSinceStart":166,"pointDateUnixMilliseconds":1681726497000,"lat":39.61858,"long":19.89747,"speed":29.96853,"speedLimit":50,"speeding":"none","phoneUsage":false},{"index":89,"secSinceStart":167,"pointDateUnixMilliseconds":1681726498000,"lat":39.61858,"long":19.89747,"speed":29.19767,"speedLimit":50,"speeding":"none","phoneUsage":false},{"index":90,"secSinceStart":168,"pointDateUnixMilliseconds":1681726499000,"lat":39.61858,"long":19.89747,"speed":29.28811,"speedLimit":50,"speeding":"none","phoneUsage":false},{"index":91,"secSinceStart":169,"pointDateUnixMilliseconds":1681726500000,"lat":39.61858,"long":19.89747,"speed":29.01489,"speedLimit":50,"speeding":"none","phoneUsage":false},{"index":92,"secSinceStart":170,"pointDateUnixMilliseconds":1681726501000,"lat":39.61858,"long":19.89747,"speed":27.9659,"speedLimit":50,"speeding":"none","phoneUsage":false},{"index":93,"secSinceStart":171,"pointDateUnixMilliseconds":1681726502000,"lat":39.61858,"long":19.89747,"speed":26.27681,"speedLimit":50,"speeding":"none","phoneUsage":false},{"index":94,"secSinceStart":172,"pointDateUnixMilliseconds":1681726503000,"lat":39.61863,"long":19.89741,"speed":24.29203,"speedLimit":50,"speeding":"none","phoneUsage":false},{"index":95,"secSinceStart":172,"pointDateUnixMilliseconds":1681726503631,"lat":39.61868,"long":19.89735,"speed":24.29203,"speedLimit":50,"speeding":"none","phoneUsage":false},{"index":96,"secSinceStart":174,"pointDateUnixMilliseconds":1681726505157,"lat":39.61878,"long":19.89718,"speed":24.29203,"speedLimit":50,"speeding":"none","phoneUsage":false},{"index":97,"secSinceStart":176,"pointDateUnixMilliseconds":1681726507000,"lat":39.61873,"long":19.89693,"speed":19.5412,"speedLimit":50,"speeding":"none","phoneUsage":false},{"index":98,"secSinceStart":177,"pointDateUnixMilliseconds":1681726508637,"lat":39.61877,"long":19.8971,"speed":19.5412,"speedLimit":50,"speeding":"none","phoneUsage":false},{"index":99,"secSinceStart":179,"pointDateUnixMilliseconds":1681726510874,"lat":39.61871,"long":19.89687,"speed":19.5412,"speedLimit":50,"speeding":"none","phoneUsage":false},{"index":100,"secSinceStart":181,"pointDateUnixMilliseconds":1681726512307,"lat":39.61875,"long":19.89678,"speed":19.5412,"speedLimit":50,"speeding":"none","phoneUsage":false},{"index":101,"secSinceStart":183,"pointDateUnixMilliseconds":1681726514759,"lat":39.61881,"long":19.89662,"speed":19.5412,"speedLimit":50,"speeding":"none","phoneUsage":false},{"index":102,"secSinceStart":185,"pointDateUnixMilliseconds":1681726516000,"lat":39.61881,"long":19.89653,"speed":14.2511,"speedLimit":50,"speeding":"none","phoneUsage":false},{"index":103,"secSinceStart":186,"pointDateUnixMilliseconds":1681726517353,"lat":39.61882,"long":19.89641,"speed":14.2511,"speedLimit":50,"speeding":"none","phoneUsage":false},{"index":104,"secSinceStart":188,"pointDateUnixMilliseconds":1681726519152,"lat":39.61891,"long":19.8963,"speed":14.2511,"speedLimit":50,"speeding":"none","phoneUsage":false},{"index":105,"secSinceStart":191,"pointDateUnixMilliseconds":1681726522000,"lat":39.61904,"long":19.89611,"speed":20.71726,"speedLimit":50,"speeding":"none","phoneUsage":false},{"index":106,"secSinceStart":193,"pointDateUnixMilliseconds":1681726524869,"lat":39.61905,"long":19.89594,"speed":20.71726,"speedLimit":50,"speeding":"none","phoneUsage":false},{"index":107,"secSinceStart":195,"pointDateUnixMilliseconds":1681726526779,"lat":39.61915,"long":19.89584,"speed":20.71726,"speedLimit":50,"speeding":"none","phoneUsage":false},{"index":108,"secSinceStart":197,"pointDateUnixMilliseconds":1681726528000,"lat":39.61921,"long":19.89577,"speed":21.21198,"speedLimit":50,"speeding":"none","phoneUsage":false},{"index":109,"secSinceStart":199,"pointDateUnixMilliseconds":1681726530099,"lat":39.61926,"long":19.89572,"speed":21.21198,"speedLimit":50,"speeding":"none","phoneUsage":false},{"index":110,"secSinceStart":203,"pointDateUnixMilliseconds":1681726534000,"lat":39.61928,"long":19.89557,"speed":21.33774,"speedLimit":50,"speeding":"none","phoneUsage":false},{"index":111,"secSinceStart":209,"pointDateUnixMilliseconds":1681726540000,"lat":39.61922,"long":19.89536,"speed":16.38658,"speedLimit":50,"speeding":"none","phoneUsage":false},{"index":112,"secSinceStart":215,"pointDateUnixMilliseconds":1681726546000,"lat":39.61914,"long":19.89513,"speed":10.15594,"speedLimit":50,"speeding":"none","phoneUsage":false},{"index":113,"secSinceStart":221,"pointDateUnixMilliseconds":1681726552000,"lat":39.61909,"long":19.89498,"speed":12.00713,"speedLimit":50,"speeding":"none","phoneUsage":false},{"index":114,"secSinceStart":227,"pointDateUnixMilliseconds":1681726558000,"lat":39.61909,"long":19.89498,"speed":7.81741,"speedLimit":50,"speeding":"none","phoneUsage":false},{"index":115,"secSinceStart":233,"pointDateUnixMilliseconds":1681726564000,"lat":39.61909,"long":19.89498,"speed":6.01986,"speedLimit":50,"speeding":"none","phoneUsage":false},{"index":116,"secSinceStart":255,"pointDateUnixMilliseconds":1681726586000,"lat":39.61909,"long":19.89498,"speed":4.50779,"speedLimit":50,"speeding":"none","phoneUsage":false},{"index":117,"secSinceStart":295,"pointDateUnixMilliseconds":1681726626677,"lat":39.61918,"long":19.89493,"speed":4.50779,"speedLimit":50,"speeding":"none","phoneUsage":false},{"index":118,"secSinceStart":341,"pointDateUnixMilliseconds":1681726672000,"lat":39.61927,"long":19.89485,"speed":3.02938,"speedLimit":50,"speeding":"none","phoneUsage":false},{"index":119,"secSinceStart":348,"pointDateUnixMilliseconds":1681726679500,"lat":39.61931,"long":19.89482,"speed":3.02938,"speedLimit":50,"speeding":"none","phoneUsage":false},{"index":120,"secSinceStart":356,"pointDateUnixMilliseconds":1681726687000,"lat":39.61935,"long":19.89479,"speed":1.96865,"speedLimit":50,"speeding":"none","phoneUsage":false},{"index":121,"secSinceStart":362,"pointDateUnixMilliseconds":1681726693000,"lat":39.61935,"long":19.89479,"speed":4.50234,"speedLimit":50,"speeding":"none","phoneUsage":false},{"index":122,"secSinceStart":368,"pointDateUnixMilliseconds":1681726699000,"lat":39.61935,"long":19.89479,"speed":5.22715,"speedLimit":50,"speeding":"none","phoneUsage":false},{"index":123,"secSinceStart":377,"pointDateUnixMilliseconds":1681726708000,"lat":39.61935,"long":19.89479,"speed":3.86569,"speedLimit":50,"speeding":"none","phoneUsage":false},{"index":124,"secSinceStart":395,"pointDateUnixMilliseconds":1681726726000,"lat":39.61935,"long":19.89479,"speed":3.72319,"speedLimit":50,"speeding":"none","phoneUsage":false},{"index":125,"secSinceStart":401,"pointDateUnixMilliseconds":1681726732000,"lat":39.61935,"long":19.89479,"speed":4.52313,"speedLimit":50,"speeding":"none","phoneUsage":false},{"index":126,"secSinceStart":407,"pointDateUnixMilliseconds":1681726738000,"lat":39.61935,"long":19.89479,"speed":5.12122,"speedLimit":50,"speeding":"none","phoneUsage":false},{"index":127,"secSinceStart":417,"pointDateUnixMilliseconds":1681726748000,"lat":39.61935,"long":19.89479,"speed":3.47612,"speedLimit":50,"speeding":"none","phoneUsage":false},{"index":128,"secSinceStart":429,"pointDateUnixMilliseconds":1681726760000,"lat":39.61935,"long":19.89479,"speed":4.42762,"speedLimit":50,"speeding":"none","phoneUsage":false},{"index":129,"secSinceStart":435,"pointDateUnixMilliseconds":1681726766000,"lat":39.61936,"long":19.89471,"speed":10.94982,"speedLimit":50,"speeding":"none","phoneUsage":false},{"index":130,"secSinceStart":441,"pointDateUnixMilliseconds":1681726772000,"lat":39.61936,"long":19.89471,"speed":13.31433,"speedLimit":50,"speeding":"none","phoneUsage":false},{"index":131,"secSinceStart":442,"pointDateUnixMilliseconds":1681726773000,"lat":39.61936,"long":19.89471,"speed":13.36529,"speedLimit":50,"speeding":"none","phoneUsage":false},{"index":132,"secSinceStart":446,"pointDateUnixMilliseconds":1681726777000,"lat":39.61936,"long":19.89471,"speed":12.42328,"speedLimit":50,"speeding":"none","phoneUsage":false},{"index":133,"secSinceStart":447,"pointDateUnixMilliseconds":1681726778000,"lat":39.61936,"long":19.89471,"speed":12.22129,"speedLimit":50,"speeding":"none","phoneUsage":false},{"index":134,"secSinceStart":448,"pointDateUnixMilliseconds":1681726779000,"lat":39.61936,"long":19.89471,"speed":12.10858,"speedLimit":50,"speeding":"none","phoneUsage":false},{"index":135,"secSinceStart":449,"pointDateUnixMilliseconds":1681726780000,"lat":39.61936,"long":19.89471,"speed":12.00251,"speedLimit":50,"speeding":"none","phoneUsage":false},{"index":136,"secSinceStart":450,"pointDateUnixMilliseconds":1681726781000,"lat":39.61936,"long":19.89471,"speed":11.77812,"speedLimit":50,"speeding":"none","phoneUsage":false},{"index":137,"secSinceStart":451,"pointDateUnixMilliseconds":1681726782000,"lat":39.61936,"long":19.89471,"speed":11.50585,"speedLimit":50,"speeding":"none","phoneUsage":false},{"index":138,"secSinceStart":452,"pointDateUnixMilliseconds":1681726783000,"lat":39.61936,"long":19.89471,"speed":11.08097,"speedLimit":50,"speeding":"none","phoneUsage":false},{"index":139,"secSinceStart":453,"pointDateUnixMilliseconds":1681726784000,"lat":39.61936,"long":19.89471,"speed":10.42746,"speedLimit":50,"speeding":"none","phoneUsage":false},{"index":140,"secSinceStart":454,"pointDateUnixMilliseconds":1681726785000,"lat":39.61936,"long":19.89471,"speed":9.8554,"speedLimit":50,"speeding":"none","phoneUsage":false},{"index":141,"secSinceStart":455,"pointDateUnixMilliseconds":1681726786000,"lat":39.61936,"long":19.89471,"speed":9.5143,"speedLimit":50,"speeding":"none","phoneUsage":false},{"index":142,"secSinceStart":457,"pointDateUnixMilliseconds":1681726788000,"lat":39.61936,"long":19.89471,"speed":9.4538,"speedLimit":50,"speeding":"none","phoneUsage":false},{"index":143,"secSinceStart":458,"pointDateUnixMilliseconds":1681726789000,"lat":39.61936,"long":19.89471,"speed":9.54979,"speedLimit":50,"speeding":"none","phoneUsage":false},{"index":144,"secSinceStart":465,"pointDateUnixMilliseconds":1681726796000,"lat":39.61936,"long":19.89471,"speed":9.77051,"speedLimit":50,"speeding":"none","phoneUsage":false},{"index":145,"secSinceStart":471,"pointDateUnixMilliseconds":1681726802000,"lat":39.61936,"long":19.89471,"speed":11.80137,"speedLimit":50,"speeding":"none","phoneUsage":false},{"index":146,"secSinceStart":477,"pointDateUnixMilliseconds":1681726808000,"lat":39.61936,"long":19.89471,"speed":10.43499,"speedLimit":50,"speeding":"none","phoneUsage":false},{"index":147,"secSinceStart":483,"pointDateUnixMilliseconds":1681726814000,"lat":39.61936,"long":19.89471,"speed":12.15293,"speedLimit":50,"speeding":"none","phoneUsage":false},{"index":148,"secSinceStart":489,"pointDateUnixMilliseconds":1681726820000,"lat":39.61936,"long":19.89471,"speed":10.93133,"speedLimit":50,"speeding":"none","phoneUsage":false}],"events":[],"related":[{"type":"Waypoints","uri":"https://api.telematicssdk.com/trips/get/admin/v1/720cf724-fdbe-44d0-b29f-ac5bb71d31b5/waypoints"}]}}